printwizard/__init__.py
printwizard/logger.py
printwizard/set_wizard_config.py
tests/__init__.py
tests/test_logger.py
printwizard-1.0.0.dist-info/LICENSE
printwizard-1.0.0.dist-info/METADATA
printwizard-1.0.0.dist-info/WHEEL
printwizard-1.0.0.dist-info/top_level.txt
printwizard-1.0.0.dist-info/RECORD
