Metadata-Version: 2.1
Name: printwizard
Version: 1.0.0
Summary: A minimal logger to make your print statements beautiful and functional
Author: GoodBoyNeon (Sushant Ray)
Author-email: <contact@neon.is-a.dev>
Classifier: Programming Language :: Python :: 3
Classifier: License :: OSI Approved :: MIT License
Classifier: Operating System :: OS Independent
License-File: LICENSE
